leonranp/InfoWindow.py
leonranp/__init__.py
leonranp/test.py
leonranp-0.1.5.dist-info/LICENSE.txt
leonranp-0.1.5.dist-info/METADATA
leonranp-0.1.5.dist-info/WHEEL
leonranp-0.1.5.dist-info/top_level.txt
leonranp-0.1.5.dist-info/RECORD
